keyoscacquire/__init__.py
keyoscacquire/__main__.py
keyoscacquire/config.py
keyoscacquire/installed_command_line_funcs.py
keyoscacquire/oscacq.py
keyoscacquire/programmes.py
keysightoscilloscopeacquire-2.0.4.dist-info/LICENSE.md
keysightoscilloscopeacquire-2.0.4.dist-info/METADATA
keysightoscilloscopeacquire-2.0.4.dist-info/WHEEL
keysightoscilloscopeacquire-2.0.4.dist-info/entry_points.txt
keysightoscilloscopeacquire-2.0.4.dist-info/top_level.txt
keysightoscilloscopeacquire-2.0.4.dist-info/RECORD
