Metadata-Version: 2.1
Name: keysightoscilloscopeacquire
Version: 2.0.4
Summary: (deprecated, new package indexed as keyoscacquire) Obtain traces, save to files and export raw plots from Keysight oscilloscopes using PyVISA.
Home-page: http://microphotonics.net/
Author: Andreas Svela
Author-email: asvela@ic.ac.uk
License: MIT
Platform: UNKNOWN
Requires-Dist: pyvisa
Requires-Dist: argparse
Requires-Dist: numpy
Requires-Dist: matplotlib
